examples/Formal/output/Guide_Doc/output/unity_test/tests/traffic_checker.sv
// Checker for traffic
module traffic_checker (
  input clk,
  input rst_n,
  input car_present,
  input [4:0] long_timer_value,
  input [4:0] short_timer_value,
  input [1:0] farm_light,
  input [1:0] hwy_light,
  input [1:0] timer_state,
  input [4:0] timer_cnt,
  input farm_start,
  input hwy_start,
  input enable_f,
  input enable_h,
  input start_t,
  input sh_t,
  input lo_t
);

  // Parameters for states
  localparam GREEN  = 2'd0;
  localparam YELLOW = 2'd1;
  localparam RED    = 2'd2;

  // ---------------------------------------------------------------------------
  // 1. FG-API: Assumptions & Protocol Constraints
  // ---------------------------------------------------------------------------

  // <CK_API_RST_SYNC> (Style: Assume)
  property CK_API_RST_SYNC;
    @(posedge clk) $rose(rst_n) |-> $past(!rst_n);
  endproperty
  M_CK_API_RST_SYNC: assume property (CK_API_RST_SYNC);

  // <CK_API_TIMER_THRESHOLD> (Style: Assume)
  property CK_API_TIMER_THRESHOLD;
    @(posedge clk) short_timer_value < long_timer_value;
  endproperty
  M_CK_API_TIMER_THRESHOLD: assume property (CK_API_TIMER_THRESHOLD);

  // <CK_API_TIMER_MIN> (Style: Assume)
  property CK_API_TIMER_MIN;
    @(posedge clk) short_timer_value > 0 && long_timer_value > 0;
  endproperty
  M_CK_API_TIMER_MIN: assume property (CK_API_TIMER_MIN);

  // <CK_API_INPUT_KNOWN> (Style: Assume)
  property CK_API_INPUT_KNOWN;
    @(posedge clk) !$isunknown({car_present, long_timer_value, short_timer_value});
  endproperty
  M_CK_API_INPUT_KNOWN: assume property (CK_API_INPUT_KNOWN);

  // ---------------------------------------------------------------------------
  // 2. FG-SAFETY: Mutual Exclusion and Illegal States
  // ---------------------------------------------------------------------------

  // <CK_SAFE_MUTEX> (Style: Comb)
  property CK_SAFE_MUTEX;
    (farm_light != RED) |-> (hwy_light == RED);
  endproperty
  A_CK_SAFE_MUTEX: assert property (CK_SAFE_MUTEX);

  // <CK_SAFE_NOT_BOTH_GREEN> (Style: Comb)
  property CK_SAFE_NOT_BOTH_GREEN;
    !(farm_light == GREEN && hwy_light == GREEN);
  endproperty
  A_CK_SAFE_NOT_BOTH_GREEN: assert property (CK_SAFE_NOT_BOTH_GREEN);

  // <CK_SAFE_NOT_BOTH_YELLOW> (Style: Comb)
  property CK_SAFE_NOT_BOTH_YELLOW;
    !(farm_light == YELLOW && hwy_light == YELLOW);
  endproperty
  A_CK_SAFE_NOT_BOTH_YELLOW: assert property (CK_SAFE_NOT_BOTH_YELLOW);

  // <CK_SAFE_FARM_VAL> (Style: Comb)
  property CK_SAFE_FARM_VAL;
    farm_light <= RED;
  endproperty
  A_CK_SAFE_FARM_VAL: assert property (CK_SAFE_FARM_VAL);

  // <CK_SAFE_HWY_VAL> (Style: Comb)
  property CK_SAFE_HWY_VAL;
    hwy_light <= RED;
  endproperty
  A_CK_SAFE_HWY_VAL: assert property (CK_SAFE_HWY_VAL);

  // ---------------------------------------------------------------------------
  // 3. FG-CONTROL: State Machines, Pointers, and Flags
  // ---------------------------------------------------------------------------

  // <CK_RESET_FARM_RED> (Style: Seq)
  property CK_RESET_FARM_RED;
    @(posedge clk) !rst_n |=> farm_light == RED;
  endproperty
  A_CK_RESET_FARM_RED: assert property (CK_RESET_FARM_RED);

  // <CK_RESET_HWY_GREEN> (Style: Seq)
  property CK_RESET_HWY_GREEN;
    @(posedge clk) !rst_n |=> hwy_light == GREEN;
  endproperty
  A_CK_RESET_HWY_GREEN: assert property (CK_RESET_HWY_GREEN);

  // <CK_FARM_G_TO_Y> (Style: Seq)
  property CK_FARM_G_TO_Y;
    @(posedge clk) disable iff (!rst_n)
    (farm_light == GREEN && (car_present == 1'b0 || lo_t)) |=> farm_light == YELLOW;
  endproperty
  A_CK_FARM_G_TO_Y: assert property (CK_FARM_G_TO_Y);

  // <CK_FARM_Y_TO_R> (Style: Seq)
  property CK_FARM_Y_TO_R;
    @(posedge clk) disable iff (!rst_n)
    (farm_light == YELLOW && sh_t) |=> farm_light == RED;
  endproperty
  A_CK_FARM_Y_TO_R: assert property (CK_FARM_Y_TO_R);

  // <CK_FARM_R_TO_G> (Style: Seq)
  property CK_FARM_R_TO_G;
    @(posedge clk) disable iff (!rst_n)
    (farm_light == RED && enable_f) |=> farm_light == GREEN;
  endproperty
  A_CK_FARM_R_TO_G: assert property (CK_FARM_R_TO_G);

  // <CK_FARM_STABLE> (Style: Seq)
  property CK_FARM_STABLE;
    @(posedge clk) disable iff (!rst_n)
    (farm_light == GREEN && car_present == 1'b1 && !lo_t) ||
    (farm_light == YELLOW && !sh_t) ||
    (farm_light == RED && !enable_f) |=> $stable(farm_light);
  endproperty
  A_CK_FARM_STABLE: assert property (CK_FARM_STABLE);

  // <CK_HWY_G_TO_Y> (Style: Seq)
  property CK_HWY_G_TO_Y;
    @(posedge clk) disable iff (!rst_n)
    (hwy_light == GREEN && (car_present == 1'b1 && lo_t)) |=> hwy_light == YELLOW;
  endproperty
  A_CK_HWY_G_TO_Y: assert property (CK_HWY_G_TO_Y);

  // <CK_HWY_Y_TO_R> (Style: Seq)
  property CK_HWY_Y_TO_R;
    @(posedge clk) disable iff (!rst_n)
    (hwy_light == YELLOW && sh_t) |=> hwy_light == RED;
  endproperty
  A_CK_HWY_Y_TO_R: assert property (CK_HWY_Y_TO_R);

  // <CK_HWY_R_TO_G> (Style: Seq)
  property CK_HWY_R_TO_G;
    @(posedge clk) disable iff (!rst_n)
    (hwy_light == RED && enable_h) |=> hwy_light == GREEN;
  endproperty
  A_CK_HWY_R_TO_G: assert property (CK_HWY_R_TO_G);

  // <CK_HWY_STABLE> (Style: Seq)
  property CK_HWY_STABLE;
    @(posedge clk) disable iff (!rst_n)
    (hwy_light == GREEN && (!car_present || !lo_t)) ||
    (hwy_light == YELLOW && !sh_t) ||
    (hwy_light == RED && !enable_h) |=> $stable(hwy_light);
  endproperty
  A_CK_HWY_STABLE: assert property (CK_HWY_STABLE);

  // <CK_TIMER_RESET> (Style: Seq)
  property CK_TIMER_RESET;
    @(posedge clk) (!rst_n || start_t) |=> timer_cnt == 0;
  endproperty
  A_CK_TIMER_RESET: assert property (CK_TIMER_RESET);

  // <CK_TIMER_INC> (Style: Seq)
  property CK_TIMER_INC;
    @(posedge clk) disable iff (!rst_n || start_t)
    (timer_state != 2'd2) |=> timer_cnt == $past(timer_cnt) + 1'b1;
  endproperty
  A_CK_TIMER_INC: assert property (CK_TIMER_INC);

  // <CK_TIMER_SHORT_VALID> (Style: Comb)
  property CK_TIMER_SHORT_VALID;
    (timer_state == 2'd1 || timer_state == 2'd2) |-> sh_t;
  endproperty
  A_CK_TIMER_SHORT_VALID: assert property (CK_TIMER_SHORT_VALID);

  // <CK_TIMER_LONG_VALID> (Style: Comb)
  property CK_TIMER_LONG_VALID;
    (timer_state == 2'd2) |-> lo_t;
  endproperty
  A_CK_TIMER_LONG_VALID: assert property (CK_TIMER_LONG_VALID);

  // ---------------------------------------------------------------------------
  // 4. FG-PROGRESS: Liveness & No-Starvation
  // ---------------------------------------------------------------------------

  // <CK_LIVE_FARM_GREEN> (Style: Seq)
  property CK_LIVE_FARM_GREEN;
    @(posedge clk) disable iff (!rst_n)
    (car_present == 1'b1) |-> s_eventually (farm_light == GREEN);
  endproperty
  A_CK_LIVE_FARM_GREEN: assert property (CK_LIVE_FARM_GREEN);

  // <CK_LIVE_HWY_GREEN> (Style: Seq)
  property CK_LIVE_HWY_GREEN;
    @(posedge clk) disable iff (!rst_n)
    (car_present == 1'b0) |-> s_eventually (hwy_light == GREEN);
  endproperty
  A_CK_LIVE_HWY_GREEN: assert property (CK_LIVE_HWY_GREEN);

  // ---------------------------------------------------------------------------
  // 5. FG-COVERAGE: Reachability Covers
  // ---------------------------------------------------------------------------

  // <CK_COVER_FARM_G> (Style: Cover)
  property CK_COVER_FARM_G;
    @(posedge clk) disable iff (!rst_n)
    farm_light == GREEN;
  endproperty
  C_CK_COVER_FARM_G: cover property (CK_COVER_FARM_G);

  // <CK_COVER_FARM_Y> (Style: Cover)
  property CK_COVER_FARM_Y;
    @(posedge clk) disable iff (!rst_n)
    farm_light == YELLOW;
  endproperty
  C_CK_COVER_FARM_Y: cover property (CK_COVER_FARM_Y);

  // <CK_COVER_HWY_Y> (Style: Cover)
  property CK_COVER_HWY_Y;
    @(posedge clk) disable iff (!rst_n)
    hwy_light == YELLOW;
  endproperty
  C_CK_COVER_HWY_Y: cover property (CK_COVER_HWY_Y);

  // <CK_COVER_HWY_R> (Style: Cover)
  property CK_COVER_HWY_R;
    @(posedge clk) disable iff (!rst_n)
    hwy_light == RED;
  endproperty
  C_CK_COVER_HWY_R: cover property (CK_COVER_HWY_R);

endmodule

examples/Formal/output/Guide_Doc/output/traffic/traffic.v
`define YES 1
`define NO 0
`define START 0
`define SHORT 1
`define LONG 2
`define GREEN 2'd0
`define YELLOW 2'd1
`define RED 2'd2
`define TIMER_WIDTH 5
`define SVA_ON 1
/*****************************************************************************/
module main(clk, reset_n, car_present, long_timer_value,
short_timer_value, farm_light, hwy_light);
input clk, reset_n, car_present;
input [`TIMER_WIDTH-1:0] long_timer_value;
input [`TIMER_WIDTH-1:0] short_timer_value;
output [1:0] farm_light;
output [1:0] hwy_light;
wire start_timer, short_timer, long_timer;
wire enable_farm, farm_start_timer, enable_hwy, hwy_start_timer;
assign start_timer = farm_start_timer || hwy_start_timer;
timer timer(.clk(clk), 
            .reset_n(reset_n), 
            .start(start_timer), 
            .short(short_timer),
            .long(long_timer), 
            .long_timer_value(long_timer_value), 
            .short_timer_value(short_timer_value));

farm_control farm_control(clk, 
                          reset_n, 
                          car_present,
                          enable_farm, 
                          short_timer, 
                          long_timer, 
                          farm_light,
                          farm_start_timer, 
                          enable_hwy);
hwy_control hwy_control (clk,  
                         reset_n,  
                         car_present,
                         enable_hwy, 
                         short_timer, 
                         long_timer, 
                         hwy_light,
                         hwy_start_timer,
                         enable_farm);


endmodule

/*****************************************************************************/
/* From the START state, the timer produces the signal
* "short" after a non-deterministic amount of time. The signal
* "short" remains asserted until the timer is reset (via the
* signal "start"). From the SHORT state, the timer produces
* the signal "long" after a non-deterministic amount of time.
* The signal "long" remains asserted until the timer is reset
* (via the signal "start").
*/
module timer(clk, reset_n, start, short, long, long_timer_value,
short_timer_value);
input clk, reset_n, start;
output short, long;
input [`TIMER_WIDTH-1:0] long_timer_value, short_timer_value;
reg [1:0] state;
reg [`TIMER_WIDTH-1:0] timer;
parameter SHORT = 1;
parameter LONG  = 2;
assign short = ((state == SHORT) || (state == LONG));
assign long = (state == `LONG);  
always @(posedge clk)
begin
  if (start || (reset_n == 1'b0)) begin
     timer <= 0;
     state <= `START;
  end
  else begin
     case (state)
     `START:
        begin
          timer <= timer + 1;
          if (timer >= short_timer_value) 
             state <= `SHORT;
        end
      `SHORT:
         begin
           timer <= timer + 1;
           if (timer >= long_timer_value) 
              state <= `LONG;
         end
endcase
end
end
//constraint2:
`ifdef SVA_ON
//long_not_be_one_in_reset_state_assume:assume property(@(posedge clk) (!reset_n) |-> (!long) );
`endif
endmodule

/****************************************************************************/
/* Farm light stays RED until it is enabled by the highway
* control. At this point, it resets the timer, and moves to
* GREEN. It stays in GREEN until there are no cars, or the
* long timer expires. At this point, it moves to YELLOW and
* resets the timer. It stays in YELLOW until the short
* timer expires. At this point, it moves to RED and enables
* the highway controller.
*/
module farm_control(clk, reset_n, car_present, enable_farm,
short_timer, long_timer, farm_light, farm_start_timer,
enable_hwy);
input clk, reset_n, car_present, enable_farm, short_timer,
long_timer;
output [1:0] farm_light;
output farm_start_timer, enable_hwy;
reg [1:0] farm_light;
assign farm_start_timer = (((farm_light == `GREEN) &&
                          ((car_present == `NO) || long_timer)) ||
                          (farm_light == `RED) && enable_farm);
assign enable_hwy = ((farm_light == `YELLOW) && short_timer);
always @(posedge clk) begin
if (reset_n == 1'b0) begin
farm_light <= `RED;
end
else begin
case (farm_light)
`GREEN:
if ((car_present == `NO) || long_timer)
farm_light <= `YELLOW;
`YELLOW:
if (short_timer) farm_light <= `RED;
`RED:
  if (enable_farm) farm_light <= `GREEN;
endcase
end
end
//If there are no more cars on the farm road when the farm light is green, the light should switch to yellow
//This condition asserts that the traffic light controller should always maximize the green time for the
//highway.


endmodule
/******************************************************************/
/* Highway light stays RED until it is enabled by the farm
* control. At this point, it resets the timer, and moves to
* GREEN. It stays in GREEN until there are cars and the
* long timer expires. At this point, it moves to YELLOW and
* resets the timer. It stays in YELLOW until the short
* timer expires. At this point, it moves to RED and enables
* the farm controller.
*/
module hwy_control(clk, reset_n, car_present, enable_hwy,
short_timer, long_timer, hwy_light, hwy_start_timer,
enable_farm);
input clk, reset_n, car_present, enable_hwy, short_timer,
long_timer;
output [1:0] hwy_light;
output hwy_start_timer, enable_farm;
reg [1:0] hwy_light;
assign hwy_start_timer =
(((hwy_light == `GREEN) && ((car_present == `YES) &&
long_timer)) || (hwy_light == `RED) && enable_hwy);
assign enable_farm = ((hwy_light == `YELLOW) &&
short_timer);
always @(posedge clk) begin
if (reset_n == 1'b0) begin
  hwy_light <= `GREEN;
end
else begin
case (hwy_light)
`GREEN:
if ((car_present ==`YES) && long_timer)
hwy_light <=`YELLOW;
`YELLOW:
if (short_timer) hwy_light <= `RED;
`RED:
  if (enable_hwy) hwy_light <= `RED;
endcase
end
end


endmodule

examples/Formal/output/Guide_Doc/output/unity_test/tests/avis/home/sfangyy/Documents/200-Work/210-Unitychip/UCAgent/examples/Formal/output/unity_test/tests/traffic_wrapper.sv
// Wrapper for traffic (main)
module traffic_wrapper (
  input clk,
  input rst_n,
  input car_present,
  input [4:0] long_timer_value,
  input [4:0] short_timer_value,
  output [1:0] farm_light,
  output [1:0] hwy_light
);

  // ---------------------------------------------------------------------------
  // DUT Instantiation
  // ---------------------------------------------------------------------------
  main dut (
    .clk(clk),
    .reset_n(rst_n),
    .car_present(car_present),
    .long_timer_value(long_timer_value),
    .short_timer_value(short_timer_value),
    .farm_light(farm_light),
    .hwy_light(hwy_light)
  );

  // ---------------------------------------------------------------------------
  // White-box Verification: Internal Signals Extraction
  // ---------------------------------------------------------------------------
  wire [1:0] timer_state = dut.timer.state;
  wire [4:0] timer_cnt   = dut.timer.timer;
  wire farm_start        = dut.farm_start_timer;
  wire hwy_start         = dut.hwy_start_timer;
  wire enable_f          = dut.enable_farm;
  wire enable_h          = dut.enable_hwy;
  wire start_t           = dut.start_timer;
  wire sh_t              = dut.short_timer;
  wire lo_t              = dut.long_timer;

  // ---------------------------------------------------------------------------
  // Checker Instantiation
  // ---------------------------------------------------------------------------
  traffic_checker checker_inst (
    .clk(clk),
    .rst_n(rst_n),
    .car_present(car_present),
    .long_timer_value(long_timer_value),
    .short_timer_value(short_timer_value),
    .farm_light(farm_light),
    .hwy_light(hwy_light),
    .timer_state(timer_state),
    .timer_cnt(timer_cnt),
    .farm_start(farm_start),
    .hwy_start(hwy_start),
    .enable_f(enable_f),
    .enable_h(enable_h),
    .start_t(start_t),
    .sh_t(sh_t),
    .lo_t(lo_t)
  );

endmodule

examples/Formal/output/Guide_Doc/output/unity_test/tests/avis/checker_inst.A_CK_LIVE_HWY_GREEN/checker_inst.A_CK_LIVE_HWY_GREEN.vcd
$date
    Mon Feb  2 15:31:03 2026
$end
$version
    AveMC 1.0
$end
$timescale
    1ns
$end
$timezero
    0ns
$end
$scope module traffic_wrapper $end
$var wire 5 * short_timer_value[4:0] $end
$var wire 1 ! clk $end
$var wire 5 ) long_timer_value[4:0] $end
$var wire 1 ' rst_n $end
$var wire 2 6 hwy_light[1:0] $end
$var wire 1 $ car_present $end
$scope module dut $end
$scope module hwy_control $end
$var reg 2 & hwy_light[1:0] $end
$upscope $end
$scope module farm_control $end
$var reg 2 # farm_light[1:0] $end
$upscope $end
$scope module timer $end
$var reg 5 ( timer[4:0] $end
$var reg 2 % state[1:0] $end
$upscope $end
$upscope $end
$scope module checker_inst $end
$var wire 1 2 A_CK_LIVE_HWY_GREEN $end
$var wire 1 3 rst_n $end
$var wire 2 5 hwy_light[1:0] $end
$var wire 1 4 car_present $end
$upscope $end
$upscope $end
$enddefinitions $end
#0
$dumpvars
1!
b10 #
1$
b00 %
b00 &
1'
b00000 (
b10000 )
b00010 *
12
13
14
b00 5
b00 6
$end
#5
0!
#10
1!
#11
b00001 (
#15
0!
#20
1!
#21
b00010 (
#25
0!
#30
1!
#31
b01 %
b00011 (
b00011 )
#35
0!
#40
1!
#41
b10 %
b00100 (
b01100 )
b00100 *
#45
0!
#50
1!
#51
b00 %
b01 &
b00000 (
b01 5
b01 6
#55
0!
#60
1!
#61
b00001 (
b01000 )
b00001 *
#65
0!
#70
1!
#71
b01 %
b00010 (
#75
0!
#80
1!
#81
b00 #
b00 %
b10 &
b00000 (
04
b10 5
b10 6
0$
#85
0!
#90
1!
#91
b01 #
#95
0!
#100
1!
#101
b00001 (
#105
0!
#110
1!
#111
b01 %
b00010 (
#115
0!
#120
1!
#121
b10 #
b00 %
b00000 (
#125
0!
#130
1!
#131
b00001 (
b00101 *
#135
0!
#140
1!
#141
b00010 (
#145
0!
#150
1!
#151
b00011 (
#155
0!
#160
1!
#161
b00100 (
#165
0!
#170
1!
#171
b00101 (
#175
0!
#180
1!
#181
b01 %
b00110 (
#185
0!
#190
1!
#191
b00111 (
b00100 )
b00001 *
#195
0!
#200
1!
#201
b10 %
b01000 (
